parallel_numpy_rng/__init__.py
parallel_numpy_rng/parallel_numpy_rng.py
parallel_numpy_rng/utils.py
parallel_numpy_rng/version.py
parallel_numpy_rng-0.2.0.dist-info/licenses/LICENSE
parallel_numpy_rng-0.2.0.dist-info/METADATA
parallel_numpy_rng-0.2.0.dist-info/WHEEL
parallel_numpy_rng-0.2.0.dist-info/top_level.txt
parallel_numpy_rng-0.2.0.dist-info/RECORD
