Metadata-Version: 2.4
Name: parallel-numpy-rng
Version: 0.2.0
Summary: Parallel random number generation that produces the same result, regardless of the number of threads
Author: Lehman Garrison
License-Expression: Apache-2.0
Project-URL: Homepage, https://github.com/lgarrison/parallel-numpy-rng/
Classifier: Programming Language :: Python :: 3
Requires-Python: >=3.10
License-File: LICENSE
Requires-Dist: numpy>=2
Requires-Dist: numba
Provides-Extra: test
Requires-Dist: pytest; extra == "test"
Dynamic: license-file
